Metadata-Version: 1.1
Name: tiktokwebapi
Version: 0.10.2
Summary: Tiktok Api.
Home-page: https://github.com/instabotai/tiktok-api
Author: Steffan Jensen
Author-email: brominercom2@gmail.com
License: Apache Software License 2.0
Keywords: tiktok,bot,api
Platform: UNKNOWN
Classifier: Development Status :: 5 - Production/Stable
Classifier: Intended Audience :: Information Technology
Classifier: License :: OSI Approved :: Apache Software License
Classifier: Programming Language :: Python :: 3.5
Classifier: Programming Language :: Python :: 3.6
Classifier: Programming Language :: Python :: 3.7
